{
  "version": "3.09.30",
  "released": "2026-06-28",
  "channel": "stable",
  "notes": "🐛 FIX NGHIỆP VỤ — Chi dự kiến (Phải trả dự kiến) không gửi duyệt được. Nguyên nhân: hiểu nhầm 'dự kiến = phải đủ hồ sơ trước'. (1) Bỏ điều kiện !_isProvisional chặn nút 'Gửi duyệt' → phiếu dự kiến draft giờ trình ký NV→KT→KTT như AP thường. (2) wfSubmit KHÔNG còn xóa _isProvisional khi gửi (hóa đơn bổ sung SAU). (3) Cờ dự kiến chỉ hết khi CÓ hóa đơn (acProvisionalShouldClear) — định nghĩa đúng 'đủ hồ sơ'. +4 test. Nghiệp vụ: chi dự kiến vẫn duyệt thanh toán trước như AP, hồ sơ bổ sung sau. Snapshot. 250 test đạt + load-test sạch.",
  "swVersion": "v3.09.30"
}
